{"version":1,"resource":"file:///home/surfiks/something/Program.cs","entries":[{"id":"J1jy.cs","timestamp":1776501018895},{"id":"TkbX.cs","timestamp":1776501109338},{"id":"tBDw.cs","timestamp":1776501133951},{"id":"Gi2A.cs","timestamp":1776501151744},{"id":"dhaq.cs","timestamp":1776501224964},{"id":"SEaa.cs","timestamp":1776501268289},{"id":"XPEU.cs","timestamp":1776501299471},{"id":"nFwq.cs","timestamp":1776501319331},{"id":"fqZb.cs","timestamp":1776501342769},{"id":"FvhF.cs","source":"undoRedo.source","timestamp":1776501349138},{"id":"VMRV.cs","timestamp":1776501351134},{"id":"YSxj.cs","timestamp":1776501507453},{"id":"tQtp.cs","timestamp":1776502409664},{"id":"DkJp.cs","timestamp":1776502425868},{"id":"LO2U.cs","timestamp":1776502443988},{"id":"l13n.cs","timestamp":1776502461245},{"id":"XPzq.cs","timestamp":1776502482288},{"id":"GGUp.cs","timestamp":1776502565704},{"id":"uSKz.cs","timestamp":1776502631423},{"id":"dC3e.cs","timestamp":1776502668992},{"id":"PLVz.cs","timestamp":1776502722833},{"id":"WzMk.cs","timestamp":1776502749409},{"id":"qxbA.cs","timestamp":1776502782434},{"id":"KCmB.cs","timestamp":1776502890265},{"id":"79Jq.cs","timestamp":1776502911460},{"id":"4P5u.cs","timestamp":1776502940058},{"id":"Ntle.cs","timestamp":1776502950468},{"id":"AmzL.cs","timestamp":1776502963201},{"id":"PdAn.cs","timestamp":1776503705475},{"id":"tKrG.cs","timestamp":1776503759601},{"id":"XfLF.cs","timestamp":1776504029676},{"id":"OsJe.cs","timestamp":1776504086812},{"id":"E4QB.cs","timestamp":1776504159117},{"id":"8sbc.cs","timestamp":1776504174321},{"id":"ILVz.cs","timestamp":1776504196536},{"id":"emF3.cs","timestamp":1776504220514},{"id":"tk1r.cs","timestamp":1776504248284},{"id":"wo6T.cs","timestamp":1776504280798},{"id":"gqDy.cs","timestamp":1776504308555},{"id":"hgZ3.cs","timestamp":1776504334070},{"id":"TQ7O.cs","timestamp":1776504379215},{"id":"wHeJ.cs","timestamp":1776504416086},{"id":"TzAs.cs","timestamp":1776504471089},{"id":"fMHc.cs","timestamp":1776504485827},{"id":"31oq.cs","timestamp":1776504497197},{"id":"JWmu.cs","timestamp":1776504562997},{"id":"32Sj.cs","timestamp":1776504589336},{"id":"Wkrp.cs","timestamp":1776504610276},{"id":"5AmD.cs","timestamp":1776504897014},{"id":"6NRp.cs","timestamp":1776505153632}]}