{"version":1,"resource":"file:///home/surfiks/.config/waybar/config","entries":[{"id":"lWCy","timestamp":1774481648511},{"id":"dKc2","timestamp":1774481679140},{"id":"DClI","source":"undoRedo.source","timestamp":1774481689877},{"id":"cULp","timestamp":1774481748512},{"id":"UVGA","timestamp":1774481882969},{"id":"LqKQ","timestamp":1774482060604},{"id":"VVLI","timestamp":1774482164052},{"id":"MMTK","timestamp":1774482298890},{"id":"FXDY","timestamp":1774482319163},{"id":"jxiN","timestamp":1774482567225},{"id":"3Ngc","timestamp":1774482646829},{"id":"bVFe","timestamp":1774482674005},{"id":"oCQM","timestamp":1774484299238},{"id":"mNsf","timestamp":1776327071579},{"id":"d1pS","timestamp":1776495939123}]}